decoratory/__init__.py
decoratory/__main__.py
decoratory/banner.py
decoratory/basic.py
decoratory/multiton.py
decoratory/observer.py
decoratory/singleton.py
decoratory/wrapper.py
decoratory-0.9.9.3.data/data/lib/site-packages/decoratory/data/License.txt
decoratory-0.9.9.3.data/data/lib/site-packages/decoratory/data/Readme.rst
decoratory-0.9.9.3.data/data/lib/site-packages/decoratory/data/Requirements.txt
decoratory-0.9.9.3.data/data/lib/site-packages/decoratory/tests/test_basic.py
decoratory-0.9.9.3.data/data/lib/site-packages/decoratory/tests/test_multiton.py
decoratory-0.9.9.3.data/data/lib/site-packages/decoratory/tests/test_observer.py
decoratory-0.9.9.3.data/data/lib/site-packages/decoratory/tests/test_singleton.py
decoratory-0.9.9.3.data/data/lib/site-packages/decoratory/tests/test_wrapper.py
decoratory-0.9.9.3.dist-info/License.txt
decoratory-0.9.9.3.dist-info/METADATA
decoratory-0.9.9.3.dist-info/WHEEL
decoratory-0.9.9.3.dist-info/top_level.txt
decoratory-0.9.9.3.dist-info/RECORD
