Metadata-Version: 2.1
Name: decoratory
Version: 0.9.9.3
Summary: Python Decorators: Singleton, SemiSingleton, Multiton, Observer, Observable, generic Wrapper.
Home-page: https://decoratory.app/index.html?ref=PyPI
Download-URL: https://decoratory.app/Section/Download.html?ref=PyPI
Author: Martin Abel
Author-email: Martin Abel <python@evation.eu>
Maintainer: Martin Abel
Maintainer-email: Martin Abel <python@evation.eu>
License: MIT
Project-URL: Projekt, https://decoratory.app/index.html?ref=PyPI
Project-URL: Release Notes, https://decoratory.app/Section/ReleaseNotes.html?ref=PyPI
Project-URL: Download, https://decoratory.app/Section/Download.html?ref=PyPI
Keywords: python decorators semi-singleton singleton multiton observer observable wrapper
Platform: Operating System :: OS Independent
Classifier: Development Status :: 4 - Beta
Classifier: Intended Audience :: Developers
Classifier: Intended Audience :: Education
Classifier: Intended Audience :: Science/Research
Classifier: Intended Audience :: Information Technology
Classifier: Natural Language :: English
Classifier: Programming Language :: Python
Classifier: Programming Language :: Python :: 3
Classifier: Programming Language :: Python :: 3.7
Classifier: Programming Language :: Python :: 3.8
Classifier: Programming Language :: Python :: 3.9
Classifier: Programming Language :: Python :: 3.10
Classifier: Programming Language :: Python :: 3.11
Classifier: License :: OSI Approved :: MIT License
Classifier: Operating System :: OS Independent
Classifier: Topic :: Education
Classifier: Topic :: Software Development
Classifier: Topic :: Software Development :: Libraries
Classifier: Topic :: Utilities
Requires-Python: >=3.7
License-File: License.txt
